gdrivewrapper/__init__.py
gdrivewrapper/service.py
gdrivewrapper/throttle.py
gdrivewrapper/wrapper.py
gdrivewrapper-0.0.17.dist-info/METADATA
gdrivewrapper-0.0.17.dist-info/WHEEL
gdrivewrapper-0.0.17.dist-info/top_level.txt
gdrivewrapper-0.0.17.dist-info/RECORD
