Metadata-Version: 2.1
Name: gdrivewrapper
Version: 0.0.17
Summary: A wrapper around Google Drive SDK
Home-page: https://github.com/jaeseopark/gdrivewrapper
Author: Jaeseo Park
License: UNKNOWN
Platform: UNKNOWN
Classifier: Programming Language :: Python :: 3
Classifier: Operating System :: OS Independent
Requires-Python: >=3
Requires-Dist: google-api-python-client
Requires-Dist: oauth2client
